ab_service/token_validator/__init__.py
ab_service/token_validator/main.py
ab_service/token_validator/schema.py
ab_service/token_validator/routes/__init__.py
ab_service/token_validator/routes/validate.py
ab_token_validator_service-0.2.0.dist-info/METADATA
ab_token_validator_service-0.2.0.dist-info/WHEEL
ab_token_validator_service-0.2.0.dist-info/licenses/LICENSE
ab_token_validator_service-0.2.0.dist-info/RECORD
